setup.py
probability_dsnd_Udacity0303/Binomialdistribution.py
probability_dsnd_Udacity0303/Gaussiandistribution.py
probability_dsnd_Udacity0303/Generaldistribution.py
probability_dsnd_Udacity0303/__init__.py
probability_dsnd_Udacity0303.egg-info/PKG-INFO
probability_dsnd_Udacity0303.egg-info/SOURCES.txt
probability_dsnd_Udacity0303.egg-info/dependency_links.txt
probability_dsnd_Udacity0303.egg-info/not-zip-safe
probability_dsnd_Udacity0303.egg-info/top_level.txt