Metadata-Version: 1.0
Name: probability-dsnd-Udacity0303
Version: 0.1
Summary: Gaussian and Binomial distributions
Home-page: UNKNOWN
Author: James Bernard Jr
Author-email: j_bernard0303@yahoo.com
License: UNKNOWN
Platform: UNKNOWN
